autoos/__init__.py
autoos-0.1.0.dist-info/WHEEL
autoos-0.1.0.dist-info/METADATA
autoos-0.1.0.dist-info/RECORD
