Metadata-Version: 2.1
Name: autoos
Version: 0.1.0
Summary: Automated Open Science (AutoOS) provides methods for the automated documentation of (autonomously conducted) experiments. These methods build on community-supported and machine-readable standards for expressing quantitative models of brain function and behavior (e.g., the Model Description Format) and corresponding data sets (e.g., the Brain Imaging Data Structure). Our tools are designed to automate the translation of those data sets into the English language and facilitate uploads the
Author: Sebastian Musslick
Author-email: sebastian_musslick@brown.edu
Requires-Python: >=3.10,<4.0
Classifier: Programming Language :: Python :: 3
Classifier: Programming Language :: Python :: 3.10
